datascientists/CHANGELOG.md
datascientists/LICENSE
datascientists/README.md
datascientists/__init__.py
datascientists/_version.py
datascientists/_config/__init__.py
datascientists/_config/pandas_config.py
datascientists/_config/plotly_config.py
datascientists/core/__init__.py
datascientists/core/config_init.py
datascientists/core/hypothesisTesting.py
datascientists/core/preprocessing.py
datascientists/core/regression.py
datascientists/core/simulation.py
datascientists/core/statisticalTest.py
datascientists-0.0.3.dist-info/METADATA
datascientists-0.0.3.dist-info/WHEEL
datascientists-0.0.3.dist-info/top_level.txt
datascientists-0.0.3.dist-info/RECORD
